junkie/__init__.py
junkie/_junkie.py
test/__init__.py
test/test_bugfix.py
test/test_dict.py
test/test_error.py
test/test_junkie.py
test/test_parameter.py
test/test_readme.py
junkie-3.0.2.dist-info/LICENSE
junkie-3.0.2.dist-info/METADATA
junkie-3.0.2.dist-info/WHEEL
junkie-3.0.2.dist-info/top_level.txt
junkie-3.0.2.dist-info/RECORD
