Metadata-Version: 2.1
Name: junkie
Version: 3.0.2
Summary: A dependency injection library for beginners and professionals
Home-page: https://github.com/sealor/junkie
Author: Stefan Richter
Classifier: Programming Language :: Python :: 3
Classifier: License :: OSI Approved :: MIT License
Classifier: Operating System :: OS Independent
Requires-Python: >=3.6
License-File: LICENSE
